mkchangelog/__about__.py
mkchangelog/__init__.py
mkchangelog/app.py
mkchangelog/config.py
mkchangelog/core.py
mkchangelog/exceptions.py
mkchangelog/hookspecs.py
mkchangelog/lib.py
mkchangelog/models.py
mkchangelog/parser.py
mkchangelog/providers.py
mkchangelog/py.typed
mkchangelog/renderers.py
mkchangelog/utils.py
mkchangelog/commands/__init__.py
mkchangelog/commands/bump.py
mkchangelog/commands/commit.py
mkchangelog/commands/generate.py
mkchangelog/commands/settings.py
mkchangelog/templates/markdown.jinja2
mkchangelog/templates/rst.jinja2
mkchangelog/templates/text.jinja2
mkchangelog-2.6.0.dist-info/METADATA
mkchangelog-2.6.0.dist-info/WHEEL
mkchangelog-2.6.0.dist-info/entry_points.txt
mkchangelog-2.6.0.dist-info/licenses/LICENSE.txt
mkchangelog-2.6.0.dist-info/RECORD
