Metadata-Version: 2.3
Name: mkchangelog
Version: 2.6.0
Summary: Generate changelog from git log with convencional commits.
Project-URL: Documentation, https://github.com/onjin/mkchangelog#readme
Project-URL: Issues, https://github.com/onjin/mkchangelog/issues
Project-URL: Source, https://github.com/onjin/mkchangelog
Author-email: Marek Wywiał <onjinx@gmail.com>
License-Expression: MIT
License-File: LICENSE.txt
Classifier: Development Status :: 5 - Production/Stable
Classifier: Intended Audience :: Developers
Classifier: Programming Language :: Python
Classifier: Programming Language :: Python :: 3.8
Classifier: Programming Language :: Python :: 3.9
Classifier: Programming Language :: Python :: 3.10
Classifier: Programming Language :: Python :: 3.11
Classifier: Programming Language :: Python :: 3.12
Classifier: Programming Language :: Python :: Implementation :: CPython
Classifier: Programming Language :: Python :: Implementation :: PyPy
Requires-Python: >=3.8
Requires-Dist: gitpython
Requires-Dist: jinja2
Requires-Dist: pluggy
Requires-Dist: rich
Requires-Dist: semver
Provides-Extra: dev
Requires-Dist: pytest-stub; extra == 'dev'
